{
  "id": "brands",
  "type": "SharedSlice",
  "name": "Brands",
  "description": "Brands",
  "variations": [
    {
      "id": "default",
      "name": "Default",
      "docURL": "...",
      "version": "initial",
      "description": "Default",
      "imageUrl": "",
      "primary": {
        "slider": {
          "type": "Boolean",
          "config": {
            "label": "Slider",
            "placeholder_false": "false",
            "placeholder_true": "true",
            "default_value": false
          }
        }
      },
      "items": {
        "logo": {
          "type": "Image",
          "config": {
            "label": "Logo",
            "constraint": {},
            "thumbnails": []
          }
        },
        "link": {
          "type": "Link",
          "config": {
            "label": "Link",
            "placeholder": "",
            "select": null
          }
        }
      }
    }
  ]
}