{
  "id": "cards",
  "type": "SharedSlice",
  "name": "Cards",
  "description": "Cards",
  "variations": [
    {
      "id": "default",
      "name": "Default",
      "docURL": "...",
      "version": "sktwi1xtmkfgx8626",
      "description": "Cards",
      "primary": {
        "alignment": {
          "type": "Select",
          "config": {
            "label": "Alignment",
            "placeholder": "",
            "options": [
              "center",
              "left",
              "right"
            ],
            "default_value": "center"
          }
        },
        "backgroundColor": {
          "type": "Select",
          "config": {
            "label": "Background Color",
            "placeholder": "",
            "options": [
              "white",
              "primary",
              "secondary",
              "muted"
            ],
            "default_value": "white"
          }
        },
        "slider": {
          "type": "Boolean",
          "config": {
            "label": "Slider",
            "placeholder_false": "false",
            "placeholder_true": "true",
            "default_value": false
          }
        },
        "imageRatio": {
          "type": "Number",
          "config": {
            "label": "Image Ratio (%)",
            "placeholder": "60"
          }
        },
        "maxColumns": {
          "type": "Select",
          "config": {
            "label": "Max Columns",
            "placeholder": "",
            "options": [
              "3",
              "4"
            ],
            "default_value": "3"
          }
        }
      },
      "imageUrl": "https://images.prismic.io/slice-machine/621a5ec4-0387-4bc5-9860-2dd46cbc07cd_default_ss.png?auto=compress,format",
      "items": {
        "image": {
          "type": "Image",
          "config": {
            "label": "Image",
            "constraint": {
              "width": null
            },
            "thumbnails": []
          }
        },
        "subtitle": {
          "type": "StructuredText",
          "config": {
            "label": "Subtitle",
            "placeholder": "Subtitle",
            "allowTargetBlank": false,
            "single": "heading6"
          }
        },
        "title": {
          "type": "StructuredText",
          "config": {
            "label": "Title",
            "placeholder": "Title",
            "allowTargetBlank": false,
            "single": "heading4"
          }
        },
        "text": {
          "type": "StructuredText",
          "config": {
            "label": "Text",
            "placeholder": "Text",
            "allowTargetBlank": true,
            "single": "paragraph,strong,em,hyperlink,list-item,o-list-item"
          }
        },
        "buttonLabel": {
          "type": "Text",
          "config": {
            "label": "Button Label",
            "placeholder": "Button Label"
          }
        },
        "buttonLink": {
          "type": "Link",
          "config": {
            "label": "Link",
            "placeholder": "Link",
            "allowTargetBlank": true,
            "select": null
          }
        }
      }
    },
    {
      "id": "withIcon",
      "name": "With Icon",
      "docURL": "...",
      "version": "sktwi1xtmkfgx8626",
      "description": "Cards",
      "primary": {
        "alignment": {
          "type": "Select",
          "config": {
            "label": "Alignment",
            "placeholder": "",
            "options": [
              "center",
              "left",
              "right"
            ],
            "default_value": "center"
          }
        },
        "backgroundColor": {
          "type": "Select",
          "config": {
            "label": "Background Color",
            "placeholder": "",
            "options": [
              "white",
              "primary",
              "secondary",
              "muted"
            ],
            "default_value": "white"
          }
        },
        "slider": {
          "type": "Boolean",
          "config": {
            "label": "Slider",
            "placeholder_false": "false",
            "placeholder_true": "true",
            "default_value": false
          }
        },
        "maxColumns": {
          "type": "Select",
          "config": {
            "label": "Max Columns",
            "placeholder": "",
            "options": [
              "3",
              "4"
            ],
            "default_value": "3"
          }
        }
      },
      "imageUrl": "https://images.prismic.io/slice-machine/621a5ec4-0387-4bc5-9860-2dd46cbc07cd_default_ss.png?auto=compress,format",
      "items": {
        "icon": {
          "type": "Text",
          "config": {
            "label": "Icon - https://iconify.design",
            "placeholder": "e.g. \"la:home\""
          }
        },
        "subtitle": {
          "type": "StructuredText",
          "config": {
            "label": "Subtitle",
            "placeholder": "Subtitle",
            "allowTargetBlank": false,
            "single": "heading6"
          }
        },
        "title": {
          "type": "StructuredText",
          "config": {
            "label": "Title",
            "placeholder": "Title",
            "allowTargetBlank": false,
            "single": "heading4"
          }
        },
        "text": {
          "type": "StructuredText",
          "config": {
            "label": "Text",
            "placeholder": "Text",
            "allowTargetBlank": true,
            "single": "paragraph,strong,em,hyperlink,list-item,o-list-item"
          }
        },
        "buttonLabel": {
          "type": "Text",
          "config": {
            "label": "Button Label",
            "placeholder": "Button Label"
          }
        },
        "buttonLink": {
          "type": "Link",
          "config": {
            "label": "Link",
            "placeholder": "Link",
            "allowTargetBlank": true,
            "select": null
          }
        }
      }
    }
  ]
}